set_game_demo/__init__.py
skyzyx_set_game_demo-1.0.1.dist-info/LICENSE.md
skyzyx_set_game_demo-1.0.1.dist-info/METADATA
skyzyx_set_game_demo-1.0.1.dist-info/WHEEL
skyzyx_set_game_demo-1.0.1.dist-info/entry_points.txt
skyzyx_set_game_demo-1.0.1.dist-info/top_level.txt
skyzyx_set_game_demo-1.0.1.dist-info/RECORD
