Metadata-Version: 2.1
Name: skyzyx-set-game-demo
Version: 1.0.1
Summary: Simple demo of the game of Set.
Home-page: https://github.com/skyzyx/set-game-demo
Author: Ryan Parman
Author-email: ryan@ryanparman.com
License: Apache License 2.0
Keywords: set demo game
Platform: UNKNOWN
Classifier: Development Status :: 3 - Alpha
Classifier: Intended Audience :: Developers
Classifier: Natural Language :: English
Classifier: License :: OSI Approved :: Apache Software License
Classifier: Programming Language :: Python
Classifier: Programming Language :: Python :: 2.7
Classifier: Programming Language :: Python :: 3
Classifier: Programming Language :: Python :: 3.3
Classifier: Programming Language :: Python :: 3.4
Classifier: Programming Language :: Python :: 3.5
Classifier: Programming Language :: Python :: 3.6
Classifier: Programming Language :: Python :: Implementation :: PyPy
Requires-Dist: autoflake (<1.0,>=0.6.6)
Requires-Dist: autopep8 (<2.0,>=1.2.4)
Requires-Dist: prettytable (<1.0,>=0.7.2)
Requires-Dist: pylint (<2.0,>=1.6.4)
Requires-Dist: six (<2.0,>=1.10.0)
